ramp_utils/__init__.py
ramp_utils/_version.py
ramp_utils/cli.py
ramp_utils/config_parser.py
ramp_utils/datasets.py
ramp_utils/deploy.py
ramp_utils/frontend.py
ramp_utils/ramp.py
ramp_utils/ramp_cli.py
ramp_utils/testing.py
ramp_utils/utils.py
ramp_utils/worker.py
ramp_utils/template/__init__.py
ramp_utils/template/database_config.yml
ramp_utils/template/database_config_template.yml
ramp_utils/template/ramp_config.yml
ramp_utils/template/ramp_config_template.yml
ramp_utils/tests/__init__.py
ramp_utils/tests/local_module.py
ramp_utils/tests/test_cli.py
ramp_utils/tests/test_config_parser.py
ramp_utils/tests/test_datasets.py
ramp_utils/tests/test_deploy.py
ramp_utils/tests/test_frontend.py
ramp_utils/tests/test_ramp.py
ramp_utils/tests/test_testing.py
ramp_utils/tests/test_utils.py
ramp_utils/tests/test_worker.py
ramp_utils/tests/data/__init__.py
ramp_utils/tests/data/ramp_config_absolute.yml
ramp_utils/tests/data/ramp_config_missing.yml
ramp_utils/tests/data/ramp_config_short.yml
ramp_utils-0.10.1.dist-info/LICENSE
ramp_utils-0.10.1.dist-info/METADATA
ramp_utils-0.10.1.dist-info/WHEEL
ramp_utils-0.10.1.dist-info/entry_points.txt
ramp_utils-0.10.1.dist-info/top_level.txt
ramp_utils-0.10.1.dist-info/RECORD
